sklearn_fuzzy/__init__.py
sklearn_fuzzy/cluster/FuzzyCMeans.py
sklearn_fuzzy/cluster/FuzzyCMeans_.py
sklearn_fuzzy/cluster/__init__.py
sklearn_fuzzy/cluster/normalize_columns.py
sklearn_fuzzy/cluster/tests/__init__.py
sklearn_fuzzy/cluster/tests/test_fuzzycmeans.py
sklearn_fuzzy-0.0.8.dist-info/LICENSE
sklearn_fuzzy-0.0.8.dist-info/METADATA
sklearn_fuzzy-0.0.8.dist-info/WHEEL
sklearn_fuzzy-0.0.8.dist-info/top_level.txt
sklearn_fuzzy-0.0.8.dist-info/RECORD
