Metadata-Version: 2.1
Name: sklearn-fuzzy
Version: 0.0.8
Summary: `sklearn_fuzzy` is a fork from `scikit-fuzzy` package with sklearn-ish methods.
Home-page: https://github.com/andersonvaf/sklearn_fuzzy
Author: Anderson Vinicius
Author-email: andersonvaf@gmail.com
License: UNKNOWN
Platform: UNKNOWN
Classifier: Programming Language :: Python :: 3
Classifier: License :: OSI Approved :: MIT License
Classifier: Operating System :: OS Independent
